odoo/addons/mass_mailing_subscription_date/README.rst
odoo/addons/mass_mailing_subscription_date/__init__.py
odoo/addons/mass_mailing_subscription_date/__manifest__.py
odoo/addons/mass_mailing_subscription_date/hooks.py
odoo/addons/mass_mailing_subscription_date/i18n/es.po
odoo/addons/mass_mailing_subscription_date/i18n/it.po
odoo/addons/mass_mailing_subscription_date/i18n/mass_mailing_subscription_date.pot
odoo/addons/mass_mailing_subscription_date/models/__init__.py
odoo/addons/mass_mailing_subscription_date/models/mailing_contact_subscription.py
odoo/addons/mass_mailing_subscription_date/readme/CONTRIBUTORS.rst
odoo/addons/mass_mailing_subscription_date/readme/DESCRIPTION.rst
odoo/addons/mass_mailing_subscription_date/static/description/icon.png
odoo/addons/mass_mailing_subscription_date/static/description/index.html
odoo/addons/mass_mailing_subscription_date/tests/__init__.py
odoo/addons/mass_mailing_subscription_date/tests/test_subscription_date.py
odoo/addons/mass_mailing_subscription_date/views/mailing_contact_subscription.xml
odoo14_addon_mass_mailing_subscription_date-14.0.1.0.1.dev10.dist-info/METADATA
odoo14_addon_mass_mailing_subscription_date-14.0.1.0.1.dev10.dist-info/WHEEL
odoo14_addon_mass_mailing_subscription_date-14.0.1.0.1.dev10.dist-info/top_level.txt
odoo14_addon_mass_mailing_subscription_date-14.0.1.0.1.dev10.dist-info/RECORD
